[
    {
        "id": "she-called-me-a-starseed",
        "title": "she called me a starseed",
        "year": 2025,
        "medium": "Acrylic on Canvas",
        "dimensions": "35\" × 25.5\"",
        "image_url": "https://images.unsplash.com/photo-1541701494587-cb58502866ab?q=80&w=2000&fm=webp",
        "thumbnail_url": "https://images.unsplash.com/photo-1541701494587-cb58502866ab?q=80&w=600&fm=webp",
        "description": "A luminous exploration of identity and cosmic connection, rendered in layers of acrylic that capture both the ethereal and the grounded.",
        "isForSale": true,
        "printUrl": null,
        "availability": "Available",
        "featured": true
    },
    {
        "id": "ancha",
        "title": "ancha",
        "year": 2024,
        "medium": "Acrylic on unstretched canvas",
        "dimensions": "26.5\" × 33\"",
        "image_url": "https://images.unsplash.com/photo-1558618666-fcd25c85cd64?q=80&w=2000&fm=webp",
        "thumbnail_url": "https://images.unsplash.com/photo-1558618666-fcd25c85cd64?q=80&w=600&fm=webp",
        "description": "Working on unstretched canvas allows for a raw, immediate quality. The surface breathes and moves with the paint.",
        "isForSale": true,
        "printUrl": null,
        "availability": "Available",
        "featured": true
    },
    {
        "id": "if-i-have-it-i-dont-keep-it",
        "title": "If I have it I don't keep it / if I keep it I don't have it",
        "year": 2024,
        "medium": "Acrylic on Canvas",
        "dimensions": "16\" × 20\"",
        "image_url": "https://images.unsplash.com/photo-1547826039-bfc35e0f1ea8?q=80&w=2000&fm=webp",
        "thumbnail_url": "https://images.unsplash.com/photo-1547826039-bfc35e0f1ea8?q=80&w=600&fm=webp",
        "description": "A meditation on paradox and impermanence. The act of holding onto something transforms it into something else entirely.",
        "isForSale": true,
        "printUrl": null,
        "availability": "Sold",
        "featured": true
    },
    {
        "id": "one-day-youll-peel-out",
        "title": "one day you'll peel out and burst into a thousand beams of light",
        "year": 2023,
        "medium": "Acrylic on Canvas",
        "dimensions": "16\" × 20\"",
        "image_url": "https://images.unsplash.com/photo-1547891654-e66ed7ebb968?q=80&w=2000&fm=webp",
        "thumbnail_url": "https://images.unsplash.com/photo-1547891654-e66ed7ebb968?q=80&w=600&fm=webp",
        "description": "An optimistic vision of transformation and transcendence. The paint layers suggest both containment and explosion.",
        "isForSale": true,
        "printUrl": null,
        "availability": "Available",
        "featured": true
    },
    {
        "id": "sh",
        "title": "SH",
        "year": 2025,
        "medium": "Acrylic on Canvas",
        "dimensions": "14\" × 11\"",
        "image_url": "https://images.unsplash.com/photo-1533158326339-7f3cf2404354?q=80&w=2000&fm=webp",
        "thumbnail_url": "https://images.unsplash.com/photo-1533158326339-7f3cf2404354?q=80&w=600&fm=webp",
        "description": "An intimate scale work exploring gesture and presence through minimal means.",
        "isForSale": true,
        "printUrl": null,
        "availability": "Available",
        "featured": false
    },
    {
        "id": "i-feel-like-im-made-out-of-light",
        "title": "I feel like I'm made out of light",
        "year": 2024,
        "medium": "Acrylic on Canvas",
        "dimensions": "8\" × 10\"",
        "image_url": "https://images.unsplash.com/photo-1518640467707-6811f4a6ab73?q=80&w=2000&fm=webp",
        "thumbnail_url": "https://images.unsplash.com/photo-1518640467707-6811f4a6ab73?q=80&w=600&fm=webp",
        "description": "A small but radiant piece capturing a moment of pure embodied lightness and joy.",
        "isForSale": true,
        "printUrl": null,
        "availability": "Available",
        "featured": false
    },
    {
        "id": "wrap-yourself-in-spikes",
        "title": "wrap yourself in spikes to keep the eyes from seeping in",
        "year": 2023,
        "medium": "Acrylic on Canvas",
        "dimensions": "16\" × 20\"",
        "image_url": "https://images.unsplash.com/photo-1579541814924-49fef17c5be5?q=80&w=2000&fm=webp",
        "thumbnail_url": "https://images.unsplash.com/photo-1579541814924-49fef17c5be5?q=80&w=600&fm=webp",
        "description": "A protective gesture against the gaze. The spikes are both armor and warning.",
        "isForSale": true,
        "printUrl": null,
        "availability": "Private Collection",
        "featured": false
    },
    {
        "id": "down-iteration-2",
        "title": "down (iteration 2)",
        "year": 2024,
        "medium": "Acrylic on Loose Canvas",
        "dimensions": "11.5\" × 16\"",
        "image_url": "https://images.unsplash.com/photo-1557672172-298e090bd0f1?q=80&w=2000&fm=webp",
        "thumbnail_url": "https://images.unsplash.com/photo-1557672172-298e090bd0f1?q=80&w=600&fm=webp",
        "description": "Part of a serial exploration. Each iteration builds on and diverges from the last.",
        "isForSale": true,
        "printUrl": null,
        "availability": "Available",
        "featured": false
    },
    {
        "id": "down-iteration-3",
        "title": "down (iteration 3)",
        "year": 2024,
        "medium": "Acrylic on Loose Canvas",
        "dimensions": "11.5\" × 16\"",
        "image_url": "https://images.unsplash.com/photo-1515378791036-0648a3ef77b2?q=80&w=2000&fm=webp",
        "thumbnail_url": "https://images.unsplash.com/photo-1515378791036-0648a3ef77b2?q=80&w=600&fm=webp",
        "description": "The third variation in the series, exploring subtle shifts in color and gesture.",
        "isForSale": true,
        "printUrl": null,
        "availability": "Available",
        "featured": false
    },
    {
        "id": "down-iteration-4",
        "title": "down (iteration 4)",
        "year": 2024,
        "medium": "Acrylic on Loose Canvas",
        "dimensions": "11.5\" × 16\"",
        "image_url": "https://images.unsplash.com/photo-1559827260-dc66d52bef19?q=80&w=2000&fm=webp",
        "thumbnail_url": "https://images.unsplash.com/photo-1559827260-dc66d52bef19?q=80&w=600&fm=webp",
        "description": "The final iteration in the current series, reaching a point of resolution.",
        "isForSale": true,
        "printUrl": null,
        "availability": "Sold",
        "featured": false
    },
    {
        "id": "cobalt-wakes-and-i-go-down",
        "title": "cobalt wakes and I go down",
        "year": 2024,
        "medium": "Acrylic on Canvas",
        "dimensions": "16\" × 20\"",
        "image_url": "https://images.unsplash.com/photo-1551732998-c91d86d39a7e?q=80&w=2000&fm=webp",
        "thumbnail_url": "https://images.unsplash.com/photo-1551732998-c91d86d39a7e?q=80&w=600&fm=webp",
        "description": "Deep blues emerge and recede. A dance between rising and falling, waking and sleeping.",
        "isForSale": true,
        "printUrl": null,
        "availability": "Available",
        "featured": false
    }
]
